X97ThingsEveryProgrammerShouldKnow/README.md
X97ThingsEveryProgrammerShouldKnow/__init__.py
X97ThingsEveryProgrammerShouldKnow/__main__.py
X97ThingsEveryProgrammerShouldKnow/file.epub
X97ThingsEveryProgrammerShouldKnow/index.html
X97ThingsEveryProgrammerShouldKnow/css/__init__.py
X97ThingsEveryProgrammerShouldKnow/css/annotations.css
X97ThingsEveryProgrammerShouldKnow/css/main.css
X97ThingsEveryProgrammerShouldKnow/css/normalize.css
X97ThingsEveryProgrammerShouldKnow/css/popup.css
X97ThingsEveryProgrammerShouldKnow/font/__init__.py
X97ThingsEveryProgrammerShouldKnow/font/fontello.eot
X97ThingsEveryProgrammerShouldKnow/font/fontello.svg
X97ThingsEveryProgrammerShouldKnow/font/fontello.ttf
X97ThingsEveryProgrammerShouldKnow/font/fontello.woff
X97ThingsEveryProgrammerShouldKnow/img/__init__.py
X97ThingsEveryProgrammerShouldKnow/img/annotator-glyph-sprite.png
X97ThingsEveryProgrammerShouldKnow/img/annotator-icon-sprite.png
X97ThingsEveryProgrammerShouldKnow/img/apple-touch-icon.png
X97ThingsEveryProgrammerShouldKnow/img/cancelfullscreen.png
X97ThingsEveryProgrammerShouldKnow/img/close.png
X97ThingsEveryProgrammerShouldKnow/img/fullscreen.png
X97ThingsEveryProgrammerShouldKnow/img/loader.gif
X97ThingsEveryProgrammerShouldKnow/img/menu-icon.png
X97ThingsEveryProgrammerShouldKnow/img/save.png
X97ThingsEveryProgrammerShouldKnow/img/saved.png
X97ThingsEveryProgrammerShouldKnow/img/settings-s.png
X97ThingsEveryProgrammerShouldKnow/img/settings.png
X97ThingsEveryProgrammerShouldKnow/img/star.png
X97ThingsEveryProgrammerShouldKnow/js/__init__.py
X97ThingsEveryProgrammerShouldKnow/js/epub.js
X97ThingsEveryProgrammerShouldKnow/js/epub.min.js
X97ThingsEveryProgrammerShouldKnow/js/epub.min.map
X97ThingsEveryProgrammerShouldKnow/js/hooks.min.js
X97ThingsEveryProgrammerShouldKnow/js/hooks.min.map
X97ThingsEveryProgrammerShouldKnow/js/reader.js
X97ThingsEveryProgrammerShouldKnow/js/reader.js.map
X97ThingsEveryProgrammerShouldKnow/js/reader.min.js
x97_things_every_programmer_should_know-2024.3.3.0.dist-info/METADATA
x97_things_every_programmer_should_know-2024.3.3.0.dist-info/WHEEL
x97_things_every_programmer_should_know-2024.3.3.0.dist-info/entry_points.txt
x97_things_every_programmer_should_know-2024.3.3.0.dist-info/top_level.txt
x97_things_every_programmer_should_know-2024.3.3.0.dist-info/RECORD
